dig_git_ignore/__init__.py
dig_git_ignore/__main__.py
dig_git_ignore/constants.py
dig_git_ignore/main.py
dig_git_ignore/provider.py
dig_git_ignore/action/__init__.py
dig_git_ignore/action/common.py
dig_git_ignore/action/find.py
dig_git_ignore/action/list_all.py
dig_git_ignore/action/template.py
dig_git_ignore/action/update.py
dig_git_ignore-1.0.2.dist-info/METADATA
dig_git_ignore-1.0.2.dist-info/WHEEL
dig_git_ignore-1.0.2.dist-info/entry_points.txt
dig_git_ignore-1.0.2.dist-info/top_level.txt
dig_git_ignore-1.0.2.dist-info/RECORD
