Metadata-Version: 2.1
Name: dig-git-ignore
Version: 1.0.2
Summary: Generate/update gitignore file with templates
Home-page: https://github.com/DIG-/python-git-ignore
Author: Gustavo de Oliveira Silva (DIG)
License: CC BY-ND 4.0
Project-URL: Bug Tracker, https://github.com/DIG-/python-git-ignore/issues
Keywords: gitignore git-ignore dig-git-ignore ignore
Classifier: Environment :: Console
Classifier: Intended Audience :: Developers
Classifier: Operating System :: OS Independent
Classifier: Topic :: Utilities
Classifier: Topic :: Software Development :: Code Generators
Classifier: Topic :: Software Development :: Version Control :: Git
Classifier: Programming Language :: Python :: 3
Classifier: Programming Language :: Python :: 3.7
Classifier: Programming Language :: Python :: 3.8
Classifier: Programming Language :: Python :: 3.9
Classifier: Programming Language :: Python :: 3.10
Classifier: Programming Language :: Python :: 3.11
Classifier: Programming Language :: Python :: 3.12
Requires-Python: >=3.7
